{
  "weight": 40,
  "density": 0.3,
  "max_height": 120,
  "min_height": 50,
  "dimension_filter": [
    "is_nether"
  ],
  "generator": {
    "type": "ellipsoid",
    "radius": [
      14,
      17
    ]
  },
  "filler": {
    "type": "ga_simple",
    "value": {
      "type": "weight_random",
      "values": [
        {
          "weight": 70,
          "value": "ore:magnetite"
        },
        {
          "weight": 60,
          "value": "ore:precious_metal"
        },
        {
          "weight": 5,
          "value": "ore:gold"
        }
      ]
    }
  }
}